dash_router/__init__.py
tests/__init__.py
tests/context.py
tests/test_dispatch.py
dash_router-0.2.0.dist-info/LICENSE
dash_router-0.2.0.dist-info/METADATA
dash_router-0.2.0.dist-info/WHEEL
dash_router-0.2.0.dist-info/top_level.txt
dash_router-0.2.0.dist-info/RECORD
