Metadata-Version: 2.1
Name: dash-router
Version: 0.2.0
Summary: A simple router for multi page Dash applications.
Home-page: https://github.com/mercyuniversityhospital/dash_router
Author: Mercy University Hosptial
Author-email: jharrington@muh.ie
License: BSD
Platform: UNKNOWN
